CLASSIFIERS.txt
MANIFEST.in
README.rst
requirements.pip
setup.py
src/cachesweeper/__init__.py
src/cachesweeper/models.py
src/cachesweeper/test_models.py
src/cachesweeper/tests.py
src/cachesweeper/utils.py
src/cachesweeper/templatetags/__init__.py
src/cachesweeper/templatetags/cachesweeper_tags.py
src/django_cache_sweeper.egg-info/PKG-INFO
src/django_cache_sweeper.egg-info/SOURCES.txt
src/django_cache_sweeper.egg-info/dependency_links.txt
src/django_cache_sweeper.egg-info/requires.txt
src/django_cache_sweeper.egg-info/top_level.txt