Metadata-Version: 1.0
Name: django-cache-sweeper
Version: 0.1.2
Summary: Lazy Django fragment cache sweeping
Home-page: http://github.com/smn/django-cache-sweeper
Author: Simon de Haan
Author-email: simon@praekeltfoundation.org
License: BSD
Platform: UNKNOWN
Classifier: Development Status :: 4 - Beta
Classifier: Intended Audience :: Developers
Classifier: License :: OSI Approved :: BSD License
Classifier: Operating System :: OS Independent
Classifier: Programming Language :: Python
Classifier: Framework :: Django
Classifier: Topic :: Software Development :: Libraries :: Python Modules
